telebot_users/__init__.py
telebot_users/async_users.py
PyTelegramBotApi_Users-1.0.dist-info/LICENSE
PyTelegramBotApi_Users-1.0.dist-info/METADATA
PyTelegramBotApi_Users-1.0.dist-info/WHEEL
PyTelegramBotApi_Users-1.0.dist-info/top_level.txt
PyTelegramBotApi_Users-1.0.dist-info/RECORD
