Metadata-Version: 2.1
Name: PyTelegramBotApi-Users
Version: 1.0
Summary: User access manager for async pyTelegramBotAPI
Home-page: https://github.com/theGENreel/PyTelegramBotAPI_Users
Author: skummer
Author-email: thegenreel@gmail.com
License: GPL3
License-File: LICENSE
Requires-Dist: pytelegrambotapi
Requires-Dist: aiofiles
Requires-Dist: aiohttp
